LICENSE
MANIFEST.in
README.md
setup.cfg
setup.py
beets_noimport.egg-info/PKG-INFO
beets_noimport.egg-info/SOURCES.txt
beets_noimport.egg-info/dependency_links.txt
beets_noimport.egg-info/requires.txt
beets_noimport.egg-info/top_level.txt
beetsplug/__init__.py
beetsplug/noimport.py