Metadata-Version: 1.1
Name: beets-noimport
Version: 0.1.0b3
Summary: add directories to the incremental import "do not import" list
Home-page: http://www.github.com/ttsda/beets-noimport
Author: Tiago Dias
Author-email: tiagoadias@gmail.com
License: MIT
Platform: ALL
Classifier: Topic :: Multimedia :: Sound/Audio
Classifier: Topic :: Multimedia :: Sound/Audio :: Players :: MP3
Classifier: License :: OSI Approved :: MIT License
Classifier: Environment :: Console
Classifier: Environment :: Web Environment
Classifier: Programming Language :: Python :: 2
Classifier: Programming Language :: Python :: 2.6
Classifier: Programming Language :: Python :: 2.7
